motivate/__init__.py
motivate/__main__.py
motivate/quotes.py
code_motivate-0.1.dist-info/LICENSE
code_motivate-0.1.dist-info/METADATA
code_motivate-0.1.dist-info/WHEEL
code_motivate-0.1.dist-info/entry_points.txt
code_motivate-0.1.dist-info/top_level.txt
code_motivate-0.1.dist-info/RECORD
